INSTALL.rst
LICENSE.txt
README.rst
setup.py
etc/h5icons.svg
examples/anim_plot.py
examples/imshow_plot.py
examples/interactive_plot.py
examples/monitor_plot.html
examples/monitor_plot.py
examples/multi_plot.py
examples/single_plot.py
examples/size_demo.py
examples/slider_plot.html
examples/slider_plot.py
examples/subplot_demo.py
mplh5canvas/__init__.py
mplh5canvas/backend_h5canvas.py
mplh5canvas/base_page.py
mplh5canvas/management_server.py
mplh5canvas/memorizingfile.py
mplh5canvas/simple_server.py
mplh5canvas.egg-info/PKG-INFO
mplh5canvas.egg-info/SOURCES.txt
mplh5canvas.egg-info/dependency_links.txt
mplh5canvas.egg-info/not-zip-safe
mplh5canvas.egg-info/requires.txt
mplh5canvas.egg-info/top_level.txt
tests/rec.py
tests/test.py