Metadata-Version: 1.0
Name: mplh5canvas
Version: 0.7
Summary: A matplotlib backend based on HTML5 Canvas.
Home-page: http://code.google.com/p/mplh5canvas/
Author: Simon Ratcliffe, Ludwig Schwardt
Author-email: sratcliffe@ska.ac.za, ludwig@ska.ac.za
License: BSD
Platform: UNKNOWN
Classifier: Environment :: Console
Classifier: Intended Audience :: Developers
Classifier: Intended Audience :: End Users/Desktop
Classifier: License :: OSI Approved :: BSD License
Classifier: Operating System :: OS Independent
Classifier: Programming Language :: Python :: 2
Classifier: Topic :: Software Development :: Libraries :: Python Modules
